CONTRIBUTING.md
MANIFEST.in
README.md
README.txt
requirements-dev.txt
requirements.txt
setup.py
Far.egg-info/PKG-INFO
Far.egg-info/SOURCES.txt
Far.egg-info/dependency_links.txt
Far.egg-info/entry_points.txt
Far.egg-info/pbr.json
Far.egg-info/top_level.txt
far/__init__.py
far/far.py
far/main.py