Metadata-Version: 1.0
Name: Far
Version: 0.0.1
Summary: Find and Replace
Home-page: https://github.com/shubhamchaudhary/far
Author: Shubham Chaudhary
Author-email: me@shubhamchaudhary.in
License: GPLv3+
Platform: UNKNOWN
